[
  {
    "Id": 0,
    "Category": "House",
    "Size": "250 sqm",
    "Price": 250000.00,
    "Town": "Sofia",
    "Street": "Vitosha",
    "PostCode": "1000",
    "Neighborhood": "Vitosha",
    "Description": "Very nice place with a nice view of the Vitosha mountain. Has a garage.",
    "DateOfBuild": "1990-03-30T00:00:00",
    "DateUntilPriceIsValid": "2022-07-29T00:00:00",
    "TypeOfBuild": "Brick"
  },
  {
    "Id": 0,
    "Category": "House",
    "Size": "240 sqm",
    "Price": 240000.00,
    "Town": "Sofia",
    "Street": "Dragalevtsi",
    "PostCode": "1000",
    "Neighborhood": "Vitosha",
    "Description": "Very nice place with a nice view of the Vitosha mountain. Has a garage.",
    "DateOfBuild": "2000-03-30T00:00:00",
    "DateUntilPriceIsValid": "2022-07-29T00:00:00",
    "TypeOfBuild": "Brick"
  },
  {
    "Id": 0,
    "Category": "House",
    "Size": "150 sqm",
    "Price": 150000.00,
    "Town": "Sofia",
    "Street": "Vitosha",
    "PostCode": "1000",
    "Neighborhood": "Vitosha",
    "Description": "Very nice place with a nice view of the Vitosha mountain. Has a garage.",
    "DateOfBuild": "1994-03-30T00:00:00",
    "DateUntilPriceIsValid": "2022-07-29T00:00:00",
    "TypeOfBuild": "Brick"
  },
  {
    "Id": 0,
    "Category": "Apartment",
    "Size": "250 sqm",
    "Price": 350000.00,
    "Town": "Sofia",
    "Street": "Center",
    "PostCode": "1000",
    "Neighborhood": "Ideal Center",
    "Description": "Very nice place with a nice view of the Vitosha mountain. Has a garage.",
    "DateOfBuild": "1954-03-30T00:00:00",
    "DateUntilPriceIsValid": "2022-07-29T00:00:00",
    "TypeOfBuild": "Brick"
  },
  {
    "Id": 0,
    "Category": "Apartment",
    "Size": "150 sqm",
    "Price": 250000.00,
    "Town": "Sofia",
    "Street": "Center",
    "PostCode": "1000",
    "Neighborhood": "Ideal Center",
    "Description": "Very nice place with a nice view of the Vitosha mountain. Has a garage.",
    "DateOfBuild": "1978-03-30T00:00:00",
    "DateUntilPriceIsValid": "2022-07-29T00:00:00",
    "TypeOfBuild": "Pannel"
  },
  {
    "Id": 0,
    "Category": "Apartment",
    "Size": "70 sqm",
    "Price": 100000.00,
    "Town": "Sofia",
    "Street": "Center",
    "PostCode": "1000",
    "Neighborhood": "Druzhba",
    "Description": "Very nice place with a nice view of the Vitosha mountain. Has a garage.",
    "DateOfBuild": "2020-03-30T00:00:00",
    "DateUntilPriceIsValid": "2022-07-29T00:00:00",
    "TypeOfBuild": "Brick"
  },
  {
    "Id": 0,
    "Category": "Apartment",
    "Size": "70 sqm",
    "Price": 100000.00,
    "Town": "Sofia",
    "Street": "Center",
    "PostCode": "1000",
    "Neighborhood": "Druzhba",
    "Description": "Very nice place with a nice view of the Vitosha mountain. Has a garage.",
    "DateOfBuild": "2020-03-30T00:00:00",
    "DateUntilPriceIsValid": "2022-07-29T00:00:00",
    "TypeOfBuild": "Brick"
  },
  {
    "Id": 0,
    "Category": "Apartment",
    "Size": "70 sqm",
    "Price": 100000.00,
    "Town": "Sofia",
    "Street": "Center",
    "PostCode": "1000",
    "Neighborhood": "Druzhba",
    "Description": "Very nice place with a nice view of the Vitosha mountain. Has a garage.",
    "DateOfBuild": "2020-03-30T00:00:00",
    "DateUntilPriceIsValid": "2022-07-29T00:00:00",
    "TypeOfBuild": "Brick"
  },
  {
    "Id": 0,
    "Category": "Apartment",
    "Size": "70 sqm",
    "Price": 100000.00,
    "Town": "Sofia",
    "Street": "Center",
    "PostCode": "1000",
    "Neighborhood": "Druzhba",
    "Description": "Very nice place with a nice view of the Vitosha mountain. Has a garage.",
    "DateOfBuild": "2020-03-30T00:00:00",
    "DateUntilPriceIsValid": "2022-07-29T00:00:00",
    "TypeOfBuild": "Brick"
  }
]